[
    {
        "data": [
            {
                "allowSdrSoftwareBrightness": false,
                "autoRotation": "InTabletMode",
                "brightness": 1,
                "colorPowerTradeoff": "PreferEfficiency",
                "colorProfileSource": "sRGB",
                "connectorName": "HDMI-A-1",
                "edidHash": "5b8c3e08c67fdc08eab893b35cc8ef2f",
                "edidIdentifier": "AUS 10066 16843009 50 2022 0",
                "highDynamicRange": false,
                "iccProfilePath": "",
                "mode": {
                    "height": 1080,
                    "refreshRate": 179821,
                    "width": 1920
                },
                "overscan": 0,
                "rgbRange": "Automatic",
                "scale": 1,
                "sdrBrightness": 200,
                "sdrGamutWideness": 0,
                "transform": "Normal",
                "vrrPolicy": "Automatic",
                "wideColorGamut": false
            }
        ],
        "name": "outputs"
    },
    {
        "data": [
            {
                "lidClosed": false,
                "outputs": [
                    {
                        "enabled": true,
                        "outputIndex": 0,
                        "position": {
                            "x": 0,
                            "y": 0
                        },
                        "priority": 0
                    }
                ]
            }
        ],
        "name": "setups"
    }
]
